{
  "timestamp": "2026-06-24T08:00:14.135555+00:00",
  "nl_query": "Which evaluators are currently in the pool for active boards but have no active script assignments, and show their faculty name, department, and the boards they are eligible for.",
  "failed_sql": "SELECT fc.name AS evaluator_name, au.display_name AS user_display_name, au.department_id, au.unit_type, au.code, au.name AS academic_unit_name, b.id AS board_id FROM evaluator_pool ep JOIN faculty_cache fc ON fc.id = ep.faculty_cache_id JOIN app_user au ON au.faculty_cache_id = fc.id JOIN board b ON b.course_id = au.id AND b.exam_id = au.id WHERE ep.is_available = TRUE AND b.status NOT IN ('CLOSED', 'SUBMITTED') AND NOT EXISTS (SELECT 1 FROM script_assignment sa WHERE sa.faculty_cache_id = ep.faculty_cache_id AND sa.is_active = TRUE) ORDER BY fc.name, au.display_name, au.department_id, au.unit_type, au.code, au.name, b.id",
  "error": "Validation failed (schema): Column validation failed: app_user does NOT have name. Use display_name instead.",
  "retries": 4,
  "corrected_sql": ""
}